gps2var/__init__.py
gps2var/core.py
gps2var-0.1.0a1.dist-info/LICENSE
gps2var-0.1.0a1.dist-info/WHEEL
gps2var-0.1.0a1.dist-info/METADATA
gps2var-0.1.0a1.dist-info/RECORD
