Metadata-Version: 2.1
Name: gps2var
Version: 0.1.0a1
Summary: Fast reading of geospatial variables by GPS coordinates
Home-page: https://github.com/cifkao/gps2var
License: MIT
Author: Ondřej Cífka
Author-email: cifkao@gmail.com
Requires-Python: >=3.7
Classifier: Intended Audience :: Science/Research
Classifier: License :: OSI Approved :: MIT License
Classifier: Operating System :: OS Independent
Classifier: Programming Language :: Python :: 3
Classifier: Programming Language :: Python :: 3.10
Classifier: Programming Language :: Python :: 3.7
Classifier: Programming Language :: Python :: 3.8
Classifier: Programming Language :: Python :: 3.9
Classifier: Topic :: Scientific/Engineering
Classifier: Topic :: Scientific/Engineering :: GIS
Classifier: Topic :: Utilities
Requires-Dist: numpy (>=1.21.5,<2.0.0)
Requires-Dist: pyproj (>=3.2.1,<4.0.0)
Requires-Dist: rasterio (>=1.2.10,<2.0.0)
Project-URL: Repository, https://github.com/cifkao/gps2var
